http_basic_auth/__init__.py
http_basic_auth/http_basic_auth.py
http_basic_auth/py.typed
fastapi_http_basic_auth_middleware-0.1.1.dist-info/LICENSE
fastapi_http_basic_auth_middleware-0.1.1.dist-info/METADATA
fastapi_http_basic_auth_middleware-0.1.1.dist-info/WHEEL
fastapi_http_basic_auth_middleware-0.1.1.dist-info/RECORD
