Metadata-Version: 2.1
Name: fastapi-http-basic-auth-middleware
Version: 0.1.1
Summary: FastAPI HTTP Basic Auth Middleware
License: BSD-3-Clause
Author: Yibu Ma
Requires-Python: >=3.12,<4.0
Classifier: License :: OSI Approved :: BSD License
Classifier: Programming Language :: Python :: 3
Classifier: Programming Language :: Python :: 3.12
Requires-Dist: fastapi (>=0.104.1,<0.105.0)
Requires-Dist: typing-extensions (>=4.8.0,<5.0.0)
